oap_dash/__init__.py
oap_dash/oap_dash.py
oap_dash/oap_utils.py
oap_dash/assets/bootstrap.css
oap_dash-0.0.2.dist-info/LICENSE
oap_dash-0.0.2.dist-info/METADATA
oap_dash-0.0.2.dist-info/WHEEL
oap_dash-0.0.2.dist-info/top_level.txt
oap_dash-0.0.2.dist-info/RECORD
