Metadata-Version: 2.1
Name: oap-dash
Version: 0.0.2
Summary: Customized Dash for OpsRamp Reports
Home-page: https://github.com/pypa/sampleproject
Author: Donald Lafranchi
Author-email: it.corridor051@gmail.com
License: UNKNOWN
Platform: UNKNOWN
Classifier: Programming Language :: Python :: 3
Classifier: License :: OSI Approved :: MIT License
Classifier: Operating System :: OS Independent
Requires-Python: >=3.6
Requires-Dist: dash (==1.16.2)
Requires-Dist: requests (==2.24.0)
